demo/demo/__init__.py
demo/demo/models.py
demo/demo/urls.py
demo/demo/views.py
django_robokassa_payments-1.3.3.dist-info/DESCRIPTION.rst
django_robokassa_payments-1.3.3.dist-info/METADATA
django_robokassa_payments-1.3.3.dist-info/RECORD
django_robokassa_payments-1.3.3.dist-info/WHEEL
django_robokassa_payments-1.3.3.dist-info/metadata.json
django_robokassa_payments-1.3.3.dist-info/top_level.txt
robokassa/__init__.py
robokassa/apps.py
robokassa/conf.py
robokassa/forms.py
robokassa/models.py
robokassa/signals.py
robokassa/tests.py
robokassa/urls.py
robokassa/views.py
robokassa/migrations/0001_initial.py
robokassa/migrations/__init__.py
robokassa/south_migrations/0001_initial.py
robokassa/south_migrations/0002_update_to_14.py
robokassa/south_migrations/__init__.py
