Metadata-Version: 1.1
Name: django-robokassa-payments
Version: 1.3.3
Summary: Приложение для интеграции платежной системы ROBOKASSA в проекты на Django.
Home-page: https://github.com/LPgenerator/django-robokassa/
Author: gotlium
Author-email: gotlium@gmail.com
License: MIT license
Platform: UNKNOWN
Classifier: Development Status :: 5 - Production/Stable
Classifier: Environment :: Web Environment
Classifier: Framework :: Django
Classifier: Intended Audience :: Developers
Classifier: License :: OSI Approved :: MIT License
Classifier: Programming Language :: Python
Classifier: Programming Language :: Python :: 2
Classifier: Programming Language :: Python :: 2.6
Classifier: Programming Language :: Python :: 2.7
Classifier: Programming Language :: Python :: 3
Classifier: Programming Language :: Python :: 3.4
Classifier: Programming Language :: Python :: 3.5
Classifier: Topic :: Software Development :: Libraries :: Python Modules
Classifier: Natural Language :: Russian
